kraut.py
kraut-0.2.dist-info/LICENSE
kraut-0.2.dist-info/WHEEL
kraut-0.2.dist-info/METADATA
kraut-0.2.dist-info/RECORD
