Metadata-Version: 2.1
Name: kraut
Version: 0.2
Summary: Compressed Pickler: kraut
Author-email: nullscry <nullscry@nullscry.com>
Classifier: License :: OSI Approved :: GNU General Public License v3 or later (GPLv3+)
Project-URL: Home, https://github.com/nullscry
